[
  {
    "id": "b_0_wav",
    "file": "https://treezfolio-philtreezs-projects.vercel.app/export/media/0.wav"
  },
  {
    "id": "b_1_wav",
    "file": "https://treezfolio-philtreezs-projects.vercel.app/export/media/1.wav"
  },
  {
    "id": "b_2_wav",
    "file": "https://treezfolio-philtreezs-projects.vercel.app/export/media/2.wav"
  },
  {
    "id": "b_3_wav",
    "file": "https://treezfolio-philtreezs-projects.vercel.app/export/media/3.wav"
  },
  {
    "id": "b_4_wav",
    "file": "https://treezfolio-philtreezs-projects.vercel.app/export/media/4.wav"
  },
  {
    "id": "b_5_wav",
    "file": "https://treezfolio-philtreezs-projects.vercel.app/export/media/5.wav"
  },
  {
    "id": "b_6_wav",
    "file": "https://treezfolio-philtreezs-projects.vercel.app/export/media/6.wav"
  },
  {
    "id": "b_7_wav",
    "file": "https://treezfolio-philtreezs-projects.vercel.app/export/media/7.wav"
  },
  {
    "id": "b_8_wav",
    "file": "https://treezfolio-philtreezs-projects.vercel.app/export/media/8.wav"
  },
  {
    "id": "b_9_wav",
    "file": "https://treezfolio-philtreezs-projects.vercel.app/export/media/9.wav"
  },
  {
    "id": "b_10_wav",
    "file": "https://treezfolio-philtreezs-projects.vercel.app/export/media/10.wav"
  },
  {
    "id": "b_11_wav",
    "file": "https://treezfolio-philtreezs-projects.vercel.app/export/media/11.wav"
  },
  {
    "id": "b_12_wav",
    "file": "https://treezfolio-philtreezs-projects.vercel.app/export/media/12.wav"
  },
  {
    "id": "b_13_wav",
    "file": "https://treezfolio-philtreezs-projects.vercel.app/export/media/13.wav"
  },
  {
    "id": "b_14_wav",
    "file": "https://treezfolio-philtreezs-projects.vercel.app/export/media/14.wav"
  },
  {
    "id": "b_15_wav",
    "file": "https://treezfolio-philtreezs-projects.vercel.app/export/media/15.wav"
  },
  {
    "id": "b_16_wav",
    "file": "https://treezfolio-philtreezs-projects.vercel.app/export/media/16.wav"
  },
  {
    "id": "b_17_wav",
    "file": "https://treezfolio-philtreezs-projects.vercel.app/export/media/17.wav"
  },
  {
    "id": "b_18_wav",
    "file": "https://treezfolio-philtreezs-projects.vercel.app/export/media/18.wav"
  },
  {
    "id": "b_19_wav",
    "file": "https://treezfolio-philtreezs-projects.vercel.app/export/media/19.wav"
  },
  {
    "id": "b_20_wav",
    "file": "https://treezfolio-philtreezs-projects.vercel.app/export/media/20.wav"
  },
  {
    "id": "b_21_wav",
    "file": "https://treezfolio-philtreezs-projects.vercel.app/export/media/21.wav"
  },
  {
    "id": "b_22_wav",
    "file": "https://treezfolio-philtreezs-projects.vercel.app/export/media/22.wav"
  },
  {
    "id": "b_23_wav",
    "file": "https://treezfolio-philtreezs-projects.vercel.app/export/media/23.wav"
  },
  {
    "id": "b_24_wav",
    "file": "https://treezfolio-philtreezs-projects.vercel.app/export/media/24.wav"
  },
  {
    "id": "b_25_wav",
    "file": "https://treezfolio-philtreezs-projects.vercel.app/export/media/25.wav"
  },
  {
    "id": "b_26_wav",
    "file": "https://treezfolio-philtreezs-projects.vercel.app/export/media/26.wav"
  },
  {
    "id": "b_27_wav",
    "file": "https://treezfolio-philtreezs-projects.vercel.app/export/media/27.wav"
  },
  {
    "id": "b_28_wav",
    "file": "https://treezfolio-philtreezs-projects.vercel.app/export/media/28.wav"
  },
  {
    "id": "b_29_wav",
    "file": "https://treezfolio-philtreezs-projects.vercel.app/export/media/29.wav"
  },
  {
    "id": "b_30_wav",
    "file": "https://treezfolio-philtreezs-projects.vercel.app/export/media/30.wav"
  },
  {
    "id": "b_31_wav",
    "file": "media/31.wav"
  },
  {
    "id": "b_32_wav",
    "file": "https://treezfolio-philtreezs-projects.vercel.app/export/media/32.wav"
  },
  {
    "id": "b_33_wav",
    "file": "https://treezfolio-philtreezs-projects.vercel.app/export/media/33.wav"
  },
  {
    "id": "b_34_wav",
    "file": "https://treezfolio-philtreezs-projects.vercel.app/export/media/34.wav"
  },
  {
    "id": "b_35_wav",
    "file": "https://treezfolio-philtreezs-projects.vercel.app/export/media/35.wav"
  },
  {
    "id": "b_36_wav",
    "file": "https://treezfolio-philtreezs-projects.vercel.app/export/media/36.wav"
  },
  {
    "id": "b_37_wav",
    "file": "https://treezfolio-philtreezs-projects.vercel.app/export/media/37.wav"
  },
  {
    "id": "b_38_wav",
    "file": "https://treezfolio-philtreezs-projects.vercel.app/export/media/38.wav"
  },
  {
    "id": "b_39_wav",
    "file": "https://treezfolio-philtreezs-projects.vercel.app/export/media/39.wav"
  },
  {
    "id": "b_40_wav",
    "file": "https://treezfolio-philtreezs-projects.vercel.app/export/media/40.wav"
  },
  {
    "id": "b_41_wav",
    "file": "https://treezfolio-philtreezs-projects.vercel.app/export/media/41.wav"
  },
  {
    "id": "b_42_wav",
    "file": "https://treezfolio-philtreezs-projects.vercel.app/export/media/42.wav"
  },
  {
    "id": "b_43_wav",
    "file": "https://treezfolio-philtreezs-projects.vercel.app/export/media/43.wav"
  },
  {
    "id": "b_44_wav",
    "file": "https://treezfolio-philtreezs-projects.vercel.app/export/media/44.wav"
  },
  {
    "id": "b_45_wav",
    "file": "https://treezfolio-philtreezs-projects.vercel.app/export/media/45.wav"
  },
  {
    "id": "b_47__wav",
    "file": "https://treezfolio-philtreezs-projects.vercel.app/export/media/47_.wav"
  },
  {
    "id": "b_48__wav",
    "file": "https://treezfolio-philtreezs-projects.vercel.app/export/media/48_.wav"
  },
  {
    "id": "b_49_wav",
    "file": "https://treezfolio-philtreezs-projects.vercel.app/export/media/49.wav"
  }
]